swml/SWMLTypes.py
swml/Sections.py
swml/SignalWireML.py
swml/__init__.py
swml_python-0.1.5.dist-info/LICENSE.txt
swml_python-0.1.5.dist-info/METADATA
swml_python-0.1.5.dist-info/WHEEL
swml_python-0.1.5.dist-info/top_level.txt
swml_python-0.1.5.dist-info/RECORD
