Metadata-Version: 2.1
Name: swml-python
Version: 0.1.5
Summary: A Python wrapper for the new SignalWire product SWML (SignalWire MarkUp Language) 
Home-page: https://github.com/Devon-White/SWML-python
Author: Devon White
Author-email: devon.white@signalwire.com
License: LICENSE.txt
Classifier: Development Status :: 3 - Alpha
Classifier: License :: OSI Approved :: MIT License
Classifier: Programming Language :: Python :: 3.8
Classifier: Programming Language :: Python :: 3.9
Classifier: Programming Language :: Python :: 3.10
Classifier: Topic :: Software Development :: Libraries :: Python Modules
Classifier: Topic :: Multimedia :: Sound/Audio :: Speech
Classifier: Topic :: Communications :: Telephony
License-File: LICENSE.txt
Requires-Dist: PyYAML (~=6.0)
